mediplot/__init__.py
mediplot/py.typed
mediplot/anatomy/__init__.py
mediplot/anatomy/body_map.py
mediplot/anatomy/organ_map.py
mediplot/assets/__init__.py
mediplot/assets/body_silhouette.png
mediplot/clinical/__init__.py
mediplot/clinical/lab_values.py
mediplot/clinical/reference_ranges.py
mediplot/clinical/vital_signs.py
mediplot/colormaps/__init__.py
mediplot/colormaps/medical.py
mediplot/core/__init__.py
mediplot/core/canvas.py
mediplot/core/shape.py
mediplot/core/types.py
mediplot/recipes/__init__.py
mediplot/recipes/parser.py
mediplot/recipes/registry.py
mediplot/recipes/data/abdomen/abdomen_arteries_anterior.json
mediplot/recipes/data/abdomen/abdomen_arteries_inferior.json
mediplot/recipes/data/abdomen/abdomen_arteries_lateral_left.json
mediplot/recipes/data/abdomen/abdomen_arteries_lateral_right.json
mediplot/recipes/data/abdomen/abdomen_arteries_posterior.json
mediplot/recipes/data/abdomen/abdomen_arteries_superior.json
mediplot/recipes/data/abdomen/abdomen_complete_anterior.json
mediplot/recipes/data/abdomen/abdomen_complete_inferior.json
mediplot/recipes/data/abdomen/abdomen_complete_lateral_left.json
mediplot/recipes/data/abdomen/abdomen_complete_lateral_right.json
mediplot/recipes/data/abdomen/abdomen_complete_posterior.json
mediplot/recipes/data/abdomen/abdomen_complete_superior.json
mediplot/recipes/data/abdomen/abdomen_gi_tract_anterior.json
mediplot/recipes/data/abdomen/abdomen_gi_tract_inferior.json
mediplot/recipes/data/abdomen/abdomen_gi_tract_lateral_left.json
mediplot/recipes/data/abdomen/abdomen_gi_tract_lateral_right.json
mediplot/recipes/data/abdomen/abdomen_gi_tract_posterior.json
mediplot/recipes/data/abdomen/abdomen_gi_tract_superior.json
mediplot/recipes/data/abdomen/abdomen_gu_system_anterior.json
mediplot/recipes/data/abdomen/abdomen_gu_system_inferior.json
mediplot/recipes/data/abdomen/abdomen_gu_system_lateral_left.json
mediplot/recipes/data/abdomen/abdomen_gu_system_lateral_right.json
mediplot-0.2.0.dist-info/METADATA
mediplot-0.2.0.dist-info/WHEEL
mediplot-0.2.0.dist-info/licenses/LICENSE
mediplot-0.2.0.dist-info/RECORD
