Metadata-Version: 2.4
Name: mediplot
Version: 0.2.0
Summary: A matplotlib-based library for anatomical visualizations, heatmaps, and body mapping
Project-URL: Homepage, https://github.com/MuteJester/MediPlot
Project-URL: Repository, https://github.com/MuteJester/MediPlot
Project-URL: Issues, https://github.com/MuteJester/MediPlot/issues
Author-email: Thomas Konstantinovsky <thomaskon90@gmail.com>
License-Expression: PolyForm-Noncommercial-1.0.0
License-File: LICENSE
Keywords: anatomy,body-map,data-visualization,heatmap,matplotlib,medical,visualization
Classifier: Development Status :: 3 - Alpha
Classifier: Intended Audience :: Developers
Classifier: Intended Audience :: Healthcare Industry
Classifier: Intended Audience :: Science/Research
Classifier: License :: Other/Proprietary License
Classifier: Operating System :: OS Independent
Classifier: Programming Language :: Python :: 3
Classifier: Programming Language :: Python :: 3.11
Classifier: Programming Language :: Python :: 3.12
Classifier: Programming Language :: Python :: 3.13
Classifier: Topic :: Scientific/Engineering :: Medical Science Apps.
Classifier: Topic :: Scientific/Engineering :: Visualization
Classifier: Typing :: Typed
Requires-Python: >=3.11
Requires-Dist: matplotlib>=3.7
Requires-Dist: numpy>=1.24
Provides-Extra: dev
Requires-Dist: mypy>=1.0; extra == 'dev'
Requires-Dist: pytest-cov>=4.0; extra == 'dev'
Requires-Dist: pytest>=7.0; extra == 'dev'
Requires-Dist: ruff>=0.1.0; extra == 'dev'
Provides-Extra: docs
Requires-Dist: sphinx-rtd-theme>=2.0; extra == 'docs'
Requires-Dist: sphinx>=7.0; extra == 'docs'
